MANIFEST.in
README.md
dexportunset.sh
distribute_setup.py
setup.py
djset/__init__.py
djset/backends.py
djset/commands.py
djset/djset.py
djset/utils.py
djset.egg-info/PKG-INFO
djset.egg-info/SOURCES.txt
djset.egg-info/dependency_links.txt
djset.egg-info/entry_points.txt
djset.egg-info/requires.txt
djset.egg-info/top_level.txt
tests/__init__.py
tests/settings.py