Metadata-Version: 1.1
Name: djset
Version: 0.2.2
Summary: Utilities for Django settings secrets
Home-page: https://github.com/bretth/djset
Author: Brett Haydon
Author-email: brett@haydon.id.au
License: LICENSE.txt
Platform: UNKNOWN
Classifier: Development Status :: 3 - Alpha
Classifier: Framework :: Django
Classifier: License :: OSI Approved :: MIT License
Classifier: Operating System :: OS Independent
Classifier: Programming Language :: Python :: 2 :: Only
Classifier: Topic :: Software Development
